qimp/Filters/Filters.py
qimp/Filters/Gates.py
qimp/Filters/__init__.py
qimp/ImageEncoding/Encodings.py
qimp/ImageEncoding/QuantumImage.py
qimp/ImageEncoding/__init__.py
qimp/__init__.py
qimp/main.py
qimp/qimp.py
qimp/requirements.txt
qimp-0.2.1.dist-info/LICENSE.rst
qimp-0.2.1.dist-info/METADATA
qimp-0.2.1.dist-info/WHEEL
qimp-0.2.1.dist-info/RECORD
