Metadata-Version: 2.1
Name: qimp
Version: 0.2.1
Summary: Quantum image manimupaltion package wrapper for Qiskit.
Home-page: https://github.com/Giacomo-Antonioli/qimp
Keywords: qimp
Author: Giacomo Antonioli
Author-email: giacomo.antonioli@phd.unipi.it
Requires-Python: >=3.8,<3.12
Classifier: Development Status :: 2 - Pre-Alpha
Classifier: Intended Audience :: Developers
Classifier: License :: OSI Approved :: MIT License
Classifier: Natural Language :: English
Classifier: Programming Language :: Python :: 3
Classifier: Programming Language :: Python :: 3.8
Classifier: Programming Language :: Python :: 3.9
Classifier: Programming Language :: Python :: 3.10
Classifier: Programming Language :: Python :: 3.11
Requires-Dist: types-tqdm (>=4.66.0.5,<5.0.0.0)
Project-URL: Bug Tracker, https://github.com/Giacomo-Antonioli/qimp/issues
Project-URL: Documentation, https://qimp.readthedocs.io
Project-URL: Repository, https://github.com/Giacomo-Antonioli/qimp
